{
  "sign_ids": [
    "hello",
    "goodbye",
    "please",
    "thank_you",
    "sorry",
    "yes",
    "no",
    "help",
    "name",
    "nice",
    "meet",
    "what",
    "how",
    "where",
    "who",
    "one",
    "two",
    "three",
    "four",
    "five",
    "eat",
    "sleep",
    "water",
    "friend",
    "deaf"
  ],
  "label_to_idx": {
    "hello": 0,
    "goodbye": 1,
    "please": 2,
    "thank_you": 3,
    "sorry": 4,
    "yes": 5,
    "no": 6,
    "help": 7,
    "name": 8,
    "nice": 9,
    "meet": 10,
    "what": 11,
    "how": 12,
    "where": 13,
    "who": 14,
    "one": 15,
    "two": 16,
    "three": 17,
    "four": 18,
    "five": 19,
    "eat": 20,
    "sleep": 21,
    "water": 22,
    "friend": 23,
    "deaf": 24
  },
  "model_version": "untrained-placeholder",
  "input_type": "3d",
  "num_frames": 24,
  "frame_size": 160
}